DCLEANGEP/__init__.py
DCLEANGEP-0.1.dist-info/METADATA
DCLEANGEP-0.1.dist-info/WHEEL
DCLEANGEP-0.1.dist-info/top_level.txt
DCLEANGEP-0.1.dist-info/RECORD
