Metadata-Version: 2.1
Name: DCLEANGEP
Version: 0.1
Summary: Python Packaging Starting Kit - Simple Structure to creater your own package - for training purposes!
Home-page: https://github.com/janamia/DCLEANGEP
Author: Group E
Author-email: jana.jindan@gmail.com
License: MIT
Platform: UNKNOWN
